{
  "last_updated": "2026-02-25 18:48:46",
  "sentiment_score": 0.0,
  "market_status": "NEUTRAL \u26aa",
  "headlines": [
    {
      "title": "Gold price today: How much 18K, 22K and 24K gold costs in your city; check rates for Delhi, Mumbai & more - The Times of India",
      "source": "The Times of India",
      "score": 0.0
    },
    {
      "title": "Gold Rate Today in India Rises; Check Latest 22K, 24K & 18K Gold Prices on 25 February 2026 - KalingaTV",
      "source": "KalingaTV",
      "score": 0.0
    },
    {
      "title": "Today Gold, Silver Rate February 25: Check 18, 22, 24 carat Gold prices in Chennai, Mumbai, Delhi, Kolkata - India.Com",
      "source": "India.Com",
      "score": 0.0
    },
    {
      "title": "Why are gold prices rising? Finance minister Nirmala Sitharaman explains - The Times of India",
      "source": "The Times of India",
      "score": 0.0
    },
    {
      "title": "Gold, Silver Rate Today Live Updates: Gold, silver prices down after seeing biggest rise in 3 weeks - The Times of India",
      "source": "The Times of India",
      "score": 0.0
    }
  ]
}